andaluh/__init__.py
andaluh/defs.py
andaluh/lib.py
andaluh-0.1.1.data/scripts/andaluh
andaluh-0.1.1.dist-info/DESCRIPTION.rst
andaluh-0.1.1.dist-info/METADATA
andaluh-0.1.1.dist-info/RECORD
andaluh-0.1.1.dist-info/WHEEL
andaluh-0.1.1.dist-info/metadata.json
andaluh-0.1.1.dist-info/top_level.txt
