Metadata-Version: 2.0
Name: andaluh
Version: 0.1.1
Summary: Transliterate español (spanish) spelling to andaluz proposals
Home-page: https://andaluh.es
Author: J. Félix Ontañón
Author-email: felixonta@gmail.com
License: GNU LESSER GENERAL PUBLIC LICENSE
Project-URL: Source Code, https://github.com/andalugeeks/andaluh-py
Platform: win32
Platform: linux2
Classifier: Topic :: Text Processing
Classifier: Topic :: Software Development :: Internationalization
Classifier: Natural Language :: Spanish
Classifier: Programming Language :: Python :: 2.7
Classifier: License :: OSI Approved :: GNU General Public License v3 (GPLv3)
